fedx/__init__.py
fedx-0.0.1a0.dist-info/LICENSE
fedx-0.0.1a0.dist-info/METADATA
fedx-0.0.1a0.dist-info/WHEEL
fedx-0.0.1a0.dist-info/top_level.txt
fedx-0.0.1a0.dist-info/RECORD
